src/__init__.py
src/topsis.py
Topsis_Kriti_102017079-1.4.dist-info/LICENSE.txt
Topsis_Kriti_102017079-1.4.dist-info/METADATA
Topsis_Kriti_102017079-1.4.dist-info/WHEEL
Topsis_Kriti_102017079-1.4.dist-info/entry_points.txt
Topsis_Kriti_102017079-1.4.dist-info/top_level.txt
Topsis_Kriti_102017079-1.4.dist-info/RECORD
