Metadata-Version: 2.1
Name: Topsis-Kriti-102017079
Version: 1.4
Summary: A convenient python package for Topsis rank and score calculation for a given dataset, weights and impacts
Home-page: https://github.com/Kriti-bit/Topsis-Kriti-102017079
Download-URL: https://github.com/Kriti-bit/Topsis-Kriti-102017079/archive/refs/tags/v0.1.tar.gz
Author: Kriti Singhal
Author-email: kritisinghal711@gmail.com
License: MIT
Keywords: python,TOPSIS,MCDM,MCDA,statistics,prescriptive analytics,cli
Classifier: Development Status :: 3 - Alpha
Classifier: Intended Audience :: Developers
Classifier: Topic :: Software Development :: Build Tools
Classifier: License :: OSI Approved :: MIT License
Classifier: Programming Language :: Python :: 3
Classifier: Programming Language :: Python :: 3.4
Classifier: Programming Language :: Python :: 3.5
Classifier: Programming Language :: Python :: 3.6
License-File: LICENSE.txt
Requires-Dist: pandas
Requires-Dist: numpy
